{
    "Response": "Success",
    "Message": "Social data successfully returned",
    "Type": 100,
    "Data": {
        "General": {
            "Name": "XWC",
            "CoinName": "WhiteCoin",
            "Type": "Webpagecoinp",
            "Points": 18502
        },
        "CryptoCompare": {
            "SimilarItems": [
                {
                    "Id": 5318,
                    "Name": "Kore",
                    "FullName": "Kore (KORE)",
                    "ImageUrl": "\/media\/14543972\/kore.png",
                    "Url": "\/coins\/kore\/",
                    "FollowingType": 1
                },
                {
                    "Id": 66259,
                    "Name": "Legends Cryptocurrency",
                    "FullName": "Legends Cryptocurrency (LGD)",
                    "ImageUrl": "\/media\/1383085\/lgd.png",
                    "Url": "\/coins\/lgd\/",
                    "FollowingType": 1
                },
                {
                    "Id": 344097,
                    "Name": "Social Media Market",
                    "FullName": "Social Media Market (SMT)",
                    "ImageUrl": "\/media\/12318350\/smt.png",
                    "Url": "\/coins\/smt\/",
                    "FollowingType": 1
                },
                {
                    "Id": 198490,
                    "Name": "REAL",
                    "FullName": "REAL (REAL)",
                    "ImageUrl": "\/media\/1383884\/rise.png",
                    "Url": "\/coins\/real\/",
                    "FollowingType": 1
                },
                {
                    "Id": 385960,
                    "Name": "Energi Token",
                    "FullName": "Energi Token (ETK)",
                    "ImageUrl": "\/media\/14913635\/etk.png",
                    "Url": "\/coins\/etk\/",
                    "FollowingType": 1
                },
                {
                    "Id": 535054,
                    "Name": "HOQU",
                    "FullName": "HOQU (HQX)",
                    "ImageUrl": "\/media\/16746735\/hqx.png",
                    "Url": "\/coins\/hqx\/",
                    "FollowingType": 1
                },
                {
                    "Id": 4600,
                    "Name": "ShadowCash",
                    "FullName": "ShadowCash (SDC)",
                    "ImageUrl": "\/media\/20419\/sdc.png",
                    "Url": "\/coins\/sdc\/",
                    "FollowingType": 1
                },
                {
                    "Id": 429355,
                    "Name": "Oyster Pearl",
                    "FullName": "Oyster Pearl (PRL)",
                    "ImageUrl": "\/media\/16746488\/prl.png",
                    "Url": "\/coins\/prl\/",
                    "FollowingType": 1
                },
                {
                    "Id": 371005,
                    "Name": "UnikoinGold",
                    "FullName": "UnikoinGold (UKG)",
                    "ImageUrl": "\/media\/14913456\/ukg.png",
                    "Url": "\/coins\/ukg\/",
                    "FollowingType": 1
                },
                {
                    "Id": 318704,
                    "Name": "Gladius",
                    "FullName": "Gladius (GLA)",
                    "ImageUrl": "\/media\/12318141\/gla.png",
                    "Url": "\/coins\/gla\/",
                    "FollowingType": 1
                }
            ],
            "CryptopianFollowers": [
                {
                    "Id": 673191,
                    "Name": "martinlion1980",
                    "ImageUrl": "https:\/\/images.cryptocompare.com\/673191\/14fb094d-39cc-4300-a9fb-55b8f8a92d7d.jpg",
                    "Url": "\/profile\/martinlion1980\/",
                    "Type": "Cryptopian"
                },
                {
                    "Id": 479761,
                    "Name": "kingbiscuit13",
                    "ImageUrl": "https:\/\/images.cryptocompare.com\/479761\/533131e6-3e76-4f85-ba30-d02d39362441.jpg",
                    "Url": "\/profile\/kingbiscuit13\/",
                    "Type": "Cryptopian"
                },
                {
                    "Id": 566861,
                    "Name": "mojo221076",
                    "ImageUrl": "https:\/\/images.cryptocompare.com\/566861\/e9c13f85-a3c6-47ff-80b3-3b241a596d2b.jpg",
                    "Url": "\/profile\/mojo221076\/",
                    "Type": "Cryptopian"
                },
                {
                    "Id": 360559,
                    "Name": "mattv53",
                    "ImageUrl": "https:\/\/images.cryptocompare.com\/360559\/158c8306-e9cb-42a5-a8f9-7a0277010233.jpg",
                    "Url": "\/profile\/mattv53\/",
                    "Type": "Cryptopian"
                },
                {
                    "Id": 290823,
                    "Name": "E2401978",
                    "ImageUrl": "https:\/\/images.cryptocompare.com\/290823\/a96b36bc-b634-40a1-9329-387968b2491f.jpg",
                    "Url": "\/profile\/E2401978\/",
                    "Type": "Cryptopian"
                },
                {
                    "Id": 386874,
                    "Name": "verbeke.thomas",
                    "ImageUrl": "https:\/\/images.cryptocompare.com\/386874\/d0efb946-476e-425b-9c8e-fd16f7b718f5.jpg",
                    "Url": "\/profile\/verbeke.thomas\/",
                    "Type": "Cryptopian"
                },
                {
                    "Id": 88964,
                    "Name": "dgimness",
                    "ImageUrl": "https:\/\/images.cryptocompare.com\/88964\/d3435d76-4b89-42f8-a489-73c09807d319.jpg",
                    "Url": "\/profile\/dgimness\/",
                    "Type": "Cryptopian"
                },
                {
                    "Id": 323057,
                    "Name": "x09089519x",
                    "ImageUrl": "https:\/\/images.cryptocompare.com\/323057\/8d2fe89b-8d67-4eda-b61d-74b9ec0b7023.jpg",
                    "Url": "\/profile\/x09089519x\/",
                    "Type": "Cryptopian"
                },
                {
                    "Id": 399735,
                    "Name": "zwljt855",
                    "ImageUrl": "https:\/\/images.cryptocompare.com\/399735\/2c9d5c29-0202-4c4b-9889-90694445cfe4.jpg",
                    "Url": "\/profile\/zwljt855\/",
                    "Type": "Cryptopian"
                },
                {
                    "Id": 192872,
                    "Name": "sulwester",
                    "ImageUrl": "https:\/\/images.cryptocompare.com\/192872\/d3ee4311-3dda-4597-9368-ebe1c6d4abba.jpg",
                    "Url": "\/profile\/sulwester\/",
                    "Type": "Cryptopian"
                },
                {
                    "Id": 501282,
                    "Name": "r.moszkowcow",
                    "ImageUrl": "https:\/\/images.cryptocompare.com\/501282\/9fde0e11-ff89-4615-a1c7-966a3e3f0a74.jpg",
                    "Url": "\/profile\/r.moszkowcow\/",
                    "Type": "Cryptopian"
                }
            ],
            "Points": 2305,
            "Followers": 78,
            "Posts": "13",
            "Comments": "3",
            "PageViewsSplit": {
                "Overview": 5281,
                "Markets": 223,
                "Analysis": 177,
                "Charts": 641,
                "Trades": 220,
                "Orderbook": 8,
                "Forum": 309,
                "Influence": 84
            },
            "PageViews": 6943
        },
        "Twitter": {
            "following": "305",
            "account_creation": "1397438951",
            "name": "WhiteCoin",
            "lists": 156,
            "statuses": 620,
            "favourites": "310",
            "followers": 14183,
            "link": "https:\/\/twitter.com\/whitecoiner",
            "Points": 14963
        },
        "Reddit": {
            "posts_per_hour": "0.00",
            "comments_per_hour": "0.04",
            "posts_per_day": "0.08",
            "comments_per_day": 0.91,
            "name": "whitecoin",
            "link": "https:\/\/www.reddit.com\/r\/whitecoin\/",
            "active_users": 35,
            "community_creation": "1397435453",
            "subscribers": 356,
            "Points": 462
        },
        "Facebook": {
            "likes": 731,
            "link": "https:\/\/www.facebook.com\/whitecoinfoundation\/",
            "is_closed": "false",
            "talking_about": "2",
            "name": "Whitecoin",
            "Points": 731
        },
        "CodeRepository": {
            "List": [
                {
                    "created_at": "1397408704",
                    "open_total_issues": "4",
                    "parent": {
                        "Name": "",
                        "Url": "",
                        "InternalId": -1
                    },
                    "size": "4177",
                    "closed_total_issues": "8",
                    "stars": 3,
                    "last_update": "1400703184",
                    "forks": 13,
                    "url": "https:\/\/github.com\/Whitecoiner\/Whitecoin",
                    "closed_issues": "0",
                    "closed_pull_issues": "8",
                    "fork": "false",
                    "last_push": "1400244078",
                    "source": {
                        "Name": "",
                        "Url": "",
                        "InternalId": -1
                    },
                    "open_pull_issues": "2",
                    "language": "C++",
                    "subscribers": 4,
                    "open_issues": "2"
                }
            ],
            "Points": 41
        }
    }
}