{
    "Response": "Success",
    "Type": 100,
    "Aggregated": true,
    "Data": [
        {
            "time": 1508025600,
            "high": 5.759e-5,
            "low": 5.599e-5,
            "open": 5.688e-5,
            "volumefrom": 63132.91,
            "volumeto": 3.59,
            "close": 5.599e-5
        },
        {
            "time": 1508284800,
            "high": 5.993e-5,
            "low": 5.576e-5,
            "open": 5.576e-5,
            "volumefrom": 0,
            "volumeto": 0,
            "close": 5.993e-5
        },
        {
            "time": 1508544000,
            "high": 6.007e-5,
            "low": 5.904e-5,
            "open": 6.007e-5,
            "volumefrom": 0,
            "volumeto": 0,
            "close": 5.904e-5
        },
        {
            "time": 1508803200,
            "high": 5.888e-5,
            "low": 5.513e-5,
            "open": 5.513e-5,
            "volumefrom": 0,
            "volumeto": 0,
            "close": 5.888e-5
        },
        {
            "time": 1509062400,
            "high": 6.148e-5,
            "low": 5.727e-5,
            "open": 5.765e-5,
            "volumefrom": 0,
            "volumeto": 0,
            "close": 6.148e-5
        },
        {
            "time": 1509321600,
            "high": 6.738e-5,
            "low": 6.124e-5,
            "open": 6.124e-5,
            "volumefrom": 0,
            "volumeto": 0,
            "close": 6.738e-5
        },
        {
            "time": 1509580800,
            "high": 7.364e-5,
            "low": 7.025e-5,
            "open": 7.025e-5,
            "volumefrom": 0,
            "volumeto": 0,
            "close": 7.364e-5
        },
        {
            "time": 1509840000,
            "high": 7.39e-5,
            "low": 6.959e-5,
            "open": 7.39e-5,
            "volumefrom": 0,
            "volumeto": 0,
            "close": 7.103e-5
        },
        {
            "time": 1510099200,
            "high": 7.444e-5,
            "low": 6.566e-5,
            "open": 7.444e-5,
            "volumefrom": 0,
            "volumeto": 0,
            "close": 6.566e-5
        },
        {
            "time": 1510358400,
            "high": 6.522e-5,
            "low": 5.878e-5,
            "open": 6.34e-5,
            "volumefrom": 0,
            "volumeto": 0,
            "close": 6.522e-5
        },
        {
            "time": 1510617600,
            "high": 7.854e-5,
            "low": 6.597e-5,
            "open": 6.597e-5,
            "volumefrom": 0,
            "volumeto": 0,
            "close": 7.854e-5
        },
        {
            "time": 1510876800,
            "high": 8.043e-5,
            "low": 7.7e-5,
            "open": 7.7e-5,
            "volumefrom": 0,
            "volumeto": 0,
            "close": 8.043e-5
        },
        {
            "time": 1511136000,
            "high": 8.245e-5,
            "low": 8.1e-5,
            "open": 8.245e-5,
            "volumefrom": 0,
            "volumeto": 0,
            "close": 8.235e-5
        },
        {
            "time": 1511395200,
            "high": 8.755e-5,
            "low": 8.013e-5,
            "open": 8.013e-5,
            "volumefrom": 0,
            "volumeto": 0,
            "close": 8.755e-5
        },
        {
            "time": 1511654400,
            "high": 9.906e-5,
            "low": 9.318e-5,
            "open": 9.318e-5,
            "volumefrom": 0,
            "volumeto": 0,
            "close": 9.906e-5
        },
        {
            "time": 1511913600,
            "high": 0.0001086,
            "low": 9.838e-5,
            "open": 9.838e-5,
            "volumefrom": 0,
            "volumeto": 0,
            "close": 0.0001086
        },
        {
            "time": 1512172800,
            "high": 0.0001162,
            "low": 0.0001091,
            "open": 0.0001091,
            "volumefrom": 0,
            "volumeto": 0,
            "close": 0.0001162
        },
        {
            "time": 1512432000,
            "high": 0.0001685,
            "low": 0.0001167,
            "open": 0.0001167,
            "volumefrom": 0,
            "volumeto": 0,
            "close": 0.0001685
        },
        {
            "time": 1512691200,
            "high": 0.0001605,
            "low": 0.0001484,
            "open": 0.0001605,
            "volumefrom": 0,
            "volumeto": 0,
            "close": 0.0001506
        },
        {
            "time": 1512950400,
            "high": 0.0001708,
            "low": 0.0001629,
            "open": 0.0001673,
            "volumefrom": 0,
            "volumeto": 0,
            "close": 0.0001629
        },
        {
            "time": 1513209600,
            "high": 0.0001935,
            "low": 0.0001647,
            "open": 0.0001647,
            "volumefrom": 0,
            "volumeto": 0,
            "close": 0.0001935
        },
        {
            "time": 1513468800,
            "high": 3.05,
            "low": 0.09762,
            "open": 2.67,
            "volumefrom": 32505.25,
            "volumeto": 17932.99,
            "close": 0.4751
        },
        {
            "time": 1513728000,
            "high": 0.5722,
            "low": 0.2051,
            "open": 0.4463,
            "volumefrom": 53072.61,
            "volumeto": 22444.94,
            "close": 0.4045
        },
        {
            "time": 1513987200,
            "high": 0.4319,
            "low": 0.2305,
            "open": 0.4261,
            "volumefrom": 37810.23,
            "volumeto": 13570.19,
            "close": 0.4091
        },
        {
            "time": 1514246400,
            "high": 0.4659,
            "low": 0.3253,
            "open": 0.4659,
            "volumefrom": 179007.93,
            "volumeto": 71831.04,
            "close": 0.401
        },
        {
            "time": 1514505600,
            "high": 1.02,
            "low": 0.3698,
            "open": 0.4008,
            "volumefrom": 923550.12,
            "volumeto": 515831.2,
            "close": 0.8096
        },
        {
            "time": 1514764800,
            "high": 2.19,
            "low": 0.6721,
            "open": 0.7859,
            "volumefrom": 765628.95,
            "volumeto": 887677.26,
            "close": 1.67
        },
        {
            "time": 1515024000,
            "high": 2.69,
            "low": 1.53,
            "open": 1.67,
            "volumefrom": 437651.21,
            "volumeto": 912510.27,
            "close": 2.44
        },
        {
            "time": 1515283200,
            "high": 2.58,
            "low": 1.91,
            "open": 2.3,
            "volumefrom": 453509.1,
            "volumeto": 1058399.46,
            "close": 2.4
        },
        {
            "time": 1515542400,
            "high": 2.57,
            "low": 1.55,
            "open": 2.48,
            "volumefrom": 518393.63,
            "volumeto": 956537.94,
            "close": 1.65
        },
        {
            "time": 1515801600,
            "high": 2.28,
            "low": 1.69,
            "open": 1.7,
            "volumefrom": 314646.01,
            "volumeto": 661730.78,
            "close": 2.01
        }
    ],
    "TimeTo": 1515974400,
    "TimeFrom": 1508025600,
    "FirstValueInArray": true,
    "ConversionType": {
        "type": "multiply",
        "conversionSymbol": "BTC"
    }
}