{
    "Response": "Success",
    "Type": 100,
    "Aggregated": true,
    "Data": [
        {
            "time": 1508025600,
            "high": 0.006278,
            "low": 0.005688,
            "open": 0.005688,
            "volumefrom": 1147.64,
            "volumeto": 7.12,
            "close": 0.006102
        },
        {
            "time": 1508284800,
            "high": 0.006212,
            "low": 0.005993,
            "open": 0.006078,
            "volumefrom": 195.02,
            "volumeto": 1.17,
            "close": 0.005993
        },
        {
            "time": 1508544000,
            "high": 0.006007,
            "low": 0.002361,
            "open": 0.006007,
            "volumefrom": 27314.77,
            "volumeto": 69.47,
            "close": 0.00242
        },
        {
            "time": 1508803200,
            "high": 0.006064,
            "low": 0.00226,
            "open": 0.00226,
            "volumefrom": 5889.94,
            "volumeto": 34.54,
            "close": 0.006064
        },
        {
            "time": 1509062400,
            "high": 0.006332,
            "low": 0.005898,
            "open": 0.005937,
            "volumefrom": 0,
            "volumeto": 0,
            "close": 0.006332
        },
        {
            "time": 1509321600,
            "high": 0.00694,
            "low": 0.003975,
            "open": 0.006308,
            "volumefrom": 5629.13,
            "volumeto": 22.38,
            "close": 0.003975
        },
        {
            "time": 1509580800,
            "high": 0.004639,
            "low": 0.004145,
            "open": 0.004145,
            "volumefrom": 26897.82,
            "volumeto": 113.88,
            "close": 0.004345
        },
        {
            "time": 1509840000,
            "high": 0.004434,
            "low": 0.004036,
            "open": 0.00436,
            "volumefrom": 7282.38,
            "volumeto": 30.07,
            "close": 0.00412
        },
        {
            "time": 1510099200,
            "high": 0.005137,
            "low": 0.003611,
            "open": 0.004318,
            "volumefrom": 9928.14,
            "volumeto": 41.59,
            "close": 0.003611
        },
        {
            "time": 1510358400,
            "high": 0.003804,
            "low": 0.003233,
            "open": 0.003487,
            "volumefrom": 23585.01,
            "volumeto": 82.43,
            "close": 0.003587
        },
        {
            "time": 1510617600,
            "high": 0.004005,
            "low": 0.003233,
            "open": 0.003628,
            "volumefrom": 20017.81,
            "volumeto": 65.93,
            "close": 0.004005
        },
        {
            "time": 1510876800,
            "high": 0.003927,
            "low": 0.003157,
            "open": 0.003927,
            "volumefrom": 91489.23,
            "volumeto": 295.99,
            "close": 0.003539
        },
        {
            "time": 1511136000,
            "high": 0.003793,
            "low": 0.003564,
            "open": 0.003628,
            "volumefrom": 7828.33,
            "volumeto": 28.58,
            "close": 0.003788
        },
        {
            "time": 1511395200,
            "high": 0.004115,
            "low": 0.003686,
            "open": 0.003686,
            "volumefrom": 1000,
            "volumeto": 3.85,
            "close": 0.004115
        },
        {
            "time": 1511654400,
            "high": 0.004557,
            "low": 0.004193,
            "open": 0.00438,
            "volumefrom": 3319.75,
            "volumeto": 14.695,
            "close": 0.004359
        },
        {
            "time": 1511913600,
            "high": 0.004779,
            "low": 0.004329,
            "open": 0.004329,
            "volumefrom": 23699.6,
            "volumeto": 103.83,
            "close": 0.004779
        },
        {
            "time": 1512172800,
            "high": 0.005115,
            "low": 0.004802,
            "open": 0.004802,
            "volumefrom": 2028.54,
            "volumeto": 10.19,
            "close": 0.005115
        },
        {
            "time": 1512432000,
            "high": 0.008088,
            "low": 0.005134,
            "open": 0.005134,
            "volumefrom": 50054.9,
            "volumeto": 371.17,
            "close": 0.007583
        },
        {
            "time": 1512691200,
            "high": 0.007221,
            "low": 0.006024,
            "open": 0.007221,
            "volumefrom": 172674.77,
            "volumeto": 1213.96,
            "close": 0.006024
        },
        {
            "time": 1512950400,
            "high": 0.006693,
            "low": 0.005187,
            "open": 0.006693,
            "volumefrom": 10461.74,
            "volumeto": 58.1,
            "close": 0.005863
        },
        {
            "time": 1513209600,
            "high": 0.006771,
            "low": 0.003521,
            "open": 0.005928,
            "volumefrom": 27095.07,
            "volumeto": 131.28,
            "close": 0.004063
        },
        {
            "time": 1513468800,
            "high": 0.01537,
            "low": 0.003984,
            "open": 0.004004,
            "volumefrom": 121806.93,
            "volumeto": 902.6,
            "close": 0.01086
        },
        {
            "time": 1513728000,
            "high": 0.01021,
            "low": 0.003622,
            "open": 0.01021,
            "volumefrom": 43396.45,
            "volumeto": 368.69,
            "close": 0.004373
        },
        {
            "time": 1513987200,
            "high": 0.005615,
            "low": 0.003034,
            "open": 0.004607,
            "volumefrom": 10936.25,
            "volumeto": 49.48,
            "close": 0.003597
        },
        {
            "time": 1514246400,
            "high": 0.008193,
            "low": 0.004097,
            "open": 0.004097,
            "volumefrom": 9413.74,
            "volumeto": 70.21,
            "close": 0.005184
        },
        {
            "time": 1514505600,
            "high": 0.00734,
            "low": 0.005181,
            "open": 0.005181,
            "volumefrom": 14943.5,
            "volumeto": 97.46,
            "close": 0.006371
        },
        {
            "time": 1514764800,
            "high": 0.006972,
            "low": 0.006185,
            "open": 0.006185,
            "volumefrom": 0,
            "volumeto": 0,
            "close": 0.006972
        },
        {
            "time": 1515024000,
            "high": 0.00893,
            "low": 0.006983,
            "open": 0.006983,
            "volumefrom": 8306.59,
            "volumeto": 70.46,
            "close": 0.008758
        },
        {
            "time": 1515283200,
            "high": 0.01331,
            "low": 0.008114,
            "open": 0.008276,
            "volumefrom": 30460.77,
            "volumeto": 363.27,
            "close": 0.008681
        },
        {
            "time": 1515542400,
            "high": 0.02462,
            "low": 0.007186,
            "open": 0.008952,
            "volumefrom": 277826.57,
            "volumeto": 2017.93,
            "close": 0.007474
        },
        {
            "time": 1515801600,
            "high": 0.03176,
            "low": 0.008261,
            "open": 0.03162,
            "volumefrom": 86887.44,
            "volumeto": 1298.2,
            "close": 0.01584
        }
    ],
    "TimeTo": 1515888000,
    "TimeFrom": 1508025600,
    "FirstValueInArray": true,
    "ConversionType": {
        "type": "multiply",
        "conversionSymbol": "BTC"
    }
}