{
    "Response": "Success",
    "Type": 100,
    "Aggregated": true,
    "Data": [
        {
            "time": 1508025600,
            "high": 0.003299,
            "low": 0.002477,
            "open": 0.003299,
            "volumefrom": 1629.96,
            "volumeto": 4.7491,
            "close": 0.003135
        },
        {
            "time": 1508284800,
            "high": 0.003122,
            "low": 0.00245,
            "open": 0.003122,
            "volumefrom": 2190.45,
            "volumeto": 5.49,
            "close": 0.002637
        },
        {
            "time": 1508544000,
            "high": 0.002643,
            "low": 0.002393,
            "open": 0.002643,
            "volumefrom": 5088.64,
            "volumeto": 12.3,
            "close": 0.00242
        },
        {
            "time": 1508803200,
            "high": 0.002649,
            "low": 0.002426,
            "open": 0.002426,
            "volumefrom": 2341.53,
            "volumeto": 5.729,
            "close": 0.002649
        },
        {
            "time": 1509062400,
            "high": 0.003135,
            "low": 0.002291,
            "open": 0.002594,
            "volumefrom": 13671.29,
            "volumeto": 38.72,
            "close": 0.003135
        },
        {
            "time": 1509321600,
            "high": 0.003123,
            "low": 0.002695,
            "open": 0.003123,
            "volumefrom": 291.99,
            "volumeto": 0.7869,
            "close": 0.002965
        },
        {
            "time": 1509580800,
            "high": 0.00324,
            "low": 0.003091,
            "open": 0.003091,
            "volumefrom": 0,
            "volumeto": 0,
            "close": 0.00324
        },
        {
            "time": 1509840000,
            "high": 0.003251,
            "low": 0.002841,
            "open": 0.003251,
            "volumefrom": 942,
            "volumeto": 2.68,
            "close": 0.002841
        },
        {
            "time": 1510099200,
            "high": 0.002978,
            "low": 0.002626,
            "open": 0.002978,
            "volumefrom": 263,
            "volumeto": 0.6906,
            "close": 0.002626
        },
        {
            "time": 1510358400,
            "high": 0.002609,
            "low": 0.002351,
            "open": 0.002536,
            "volumefrom": 0,
            "volumeto": 0,
            "close": 0.002609
        },
        {
            "time": 1510617600,
            "high": 0.003141,
            "low": 0.002356,
            "open": 0.002639,
            "volumefrom": 63112.82,
            "volumeto": 158.74,
            "close": 0.002356
        },
        {
            "time": 1510876800,
            "high": 0.002815,
            "low": 0.00231,
            "open": 0.00231,
            "volumefrom": 1242.95,
            "volumeto": 3.5,
            "close": 0.002815
        },
        {
            "time": 1511136000,
            "high": 0.002886,
            "low": 0.002835,
            "open": 0.002886,
            "volumefrom": 2961.9,
            "volumeto": 8.54,
            "close": 0.002882
        },
        {
            "time": 1511395200,
            "high": 0.003239,
            "low": 0.002805,
            "open": 0.002805,
            "volumefrom": 1910.62,
            "volumeto": 5.7306,
            "close": 0.003239
        },
        {
            "time": 1511654400,
            "high": 0.003665,
            "low": 0.00317,
            "open": 0.003448,
            "volumefrom": 52794.04,
            "volumeto": 178.17,
            "close": 0.003368
        },
        {
            "time": 1511913600,
            "high": 0.003693,
            "low": 0.003345,
            "open": 0.003345,
            "volumefrom": 698.85,
            "volumeto": 2.46,
            "close": 0.003693
        },
        {
            "time": 1512172800,
            "high": 0.00372,
            "low": 0.003599,
            "open": 0.00371,
            "volumefrom": 8656.61,
            "volumeto": 31.75,
            "close": 0.00372
        },
        {
            "time": 1512432000,
            "high": 0.005224,
            "low": 0.003733,
            "open": 0.003733,
            "volumefrom": 1172.67,
            "volumeto": 5.81,
            "close": 0.005224
        },
        {
            "time": 1512691200,
            "high": 0.004975,
            "low": 0.003711,
            "open": 0.004975,
            "volumefrom": 63703,
            "volumeto": 244.79,
            "close": 0.003765
        },
        {
            "time": 1512950400,
            "high": 0.004954,
            "low": 0.003909,
            "open": 0.004183,
            "volumefrom": 16207.97,
            "volumeto": 63.9,
            "close": 0.003909
        },
        {
            "time": 1513209600,
            "high": 0.004836,
            "low": 0.003952,
            "open": 0.003952,
            "volumefrom": 4277.05,
            "volumeto": 18.23,
            "close": 0.004836
        },
        {
            "time": 1513468800,
            "high": 0.004766,
            "low": 0.004381,
            "open": 0.004766,
            "volumefrom": 5825.21,
            "volumeto": 27.63,
            "close": 0.004381
        },
        {
            "time": 1513728000,
            "high": 0.004115,
            "low": 0.001776,
            "open": 0.004115,
            "volumefrom": 168031.33,
            "volumeto": 427.09,
            "close": 0.001776
        },
        {
            "time": 1513987200,
            "high": 0.003597,
            "low": 0.001872,
            "open": 0.001872,
            "volumefrom": 1945.48,
            "volumeto": 6.16,
            "close": 0.003597
        },
        {
            "time": 1514246400,
            "high": 0.01202,
            "low": 0.001387,
            "open": 0.004097,
            "volumefrom": 677390.09,
            "volumeto": 2397.35,
            "close": 0.003312
        },
        {
            "time": 1514505600,
            "high": 0.003878,
            "low": 0.003133,
            "open": 0.00331,
            "volumefrom": 4223.94,
            "volumeto": 16.04,
            "close": 0.003878
        },
        {
            "time": 1514764800,
            "high": 0.004395,
            "low": 0.003765,
            "open": 0.003765,
            "volumefrom": 425.01,
            "volumeto": 1.87,
            "close": 0.004395
        },
        {
            "time": 1515024000,
            "high": 0.005152,
            "low": 0.004402,
            "open": 0.004402,
            "volumefrom": 13217.34,
            "volumeto": 63.86,
            "close": 0.004808
        },
        {
            "time": 1515283200,
            "high": 0.005092,
            "low": 0.004493,
            "open": 0.004544,
            "volumefrom": 43815.51,
            "volumeto": 216.6,
            "close": 0.004919
        },
        {
            "time": 1515542400,
            "high": 0.005073,
            "low": 0.003992,
            "open": 0.005073,
            "volumefrom": 8557.04,
            "volumeto": 39.61,
            "close": 0.004152
        },
        {
            "time": 1515801600,
            "high": 0.01723,
            "low": 0.008242,
            "open": 0.01439,
            "volumefrom": 296718.64,
            "volumeto": 3581.87,
            "close": 0.008255
        }
    ],
    "TimeTo": 1515888000,
    "TimeFrom": 1508025600,
    "FirstValueInArray": true,
    "ConversionType": {
        "type": "multiply",
        "conversionSymbol": "BTC"
    }
}