{
    "Response": "Success",
    "Message": "Coin full snapshot successfully returned",
    "Data": {
        "SEO": {
            "PageTitle": "ChipCoin (CHIP) - Overview, Forum, Live Streaming Markets, Charts and Trades",
            "PageDescription": "A coin again with not too much information available as their website is down.",
            "BaseUrl": "https:\/\/www.cryptocompare.com",
            "BaseImageUrl": "https:\/\/www.cryptocompare.com",
            "OgImageUrl": "\/media\/20685\/chip.png",
            "OgImageWidth": "300",
            "OgImageHeight": "300"
        },
        "General": {
            "Id": "8696",
            "DocumentType": "Webpagecoinp",
            "H1Text": "ChipCoin (CHIP)",
            "DangerTop": "",
            "WarningTop": "",
            "InfoTop": "",
            "Symbol": "CHIP",
            "Url": "\/coins\/chip\/",
            "BaseAngularUrl": "\/coins\/chip\/",
            "Name": "Chip",
            "ImageUrl": "\/media\/20685\/chip.png",
            "Description": "<p>A coin again with not too much information available as their website is down.<\/p>",
            "Features": "",
            "Technology": "",
            "TotalCoinSupply": "0",
            "Algorithm": "X11",
            "ProofType": "PoW",
            "StartDate": "25\/07\/2015",
            "Twitter": "",
            "Website": "-",
            "AffiliateUrl": "-",
            "Sponsor": {
                "TextTop": "Sponsored by",
                "Link": "http:\/\/wepowernetwork.go2cloud.org\/aff_c?offer_id=2&aff_id=1001",
                "ImageUrl": "\/media\/20780605\/2.png"
            },
            "LastBlockExplorerUpdateTS": "",
            "DifficultyAdjustment": "",
            "BlockRewardReduction": "",
            "BlockNumber": "",
            "BlockTime": "",
            "NetHashesPerSecond": "",
            "TotalCoinsMined": "",
            "PreviousTotalCoinsMined": "",
            "BlockReward": ""
        },
        "ICO": {
            "Status": "N\/A",
            "WhitePaper": "-"
        },
        "Subs": [
            "2~Novaexchange~CHIP~BTC",
            "2~Novaexchange~CHIP~DOGE",
            "2~CCEX~CHIP~BTC",
            "2~Yobit~CHIP~DOGE",
            "2~Yobit~CHIP~BTC",
            "2~CCEX~CHIP~USD",
            "2~Yobit~CHIP~USD",
            "2~Yobit~CHIP~RUR",
            "2~CCEX~CHIP~DOGE",
            "2~Yobit~CHIP~ETH",
            "2~Yobit~CHIP~WAVES"
        ],
        "StreamerDataRaw": [
            "5~CCCAGG~CHIP~BTC~4~2.7e-7~1515935103~944.32977777~0.0002549690399979~200000005~2792.29274073~0.0007539190399971001~2792.29274073~0.0007539190399971001~2.7e-7~2.7e-7~2.7e-7~2.7e-7~2.7e-7~2.7e-7~Yobit~7ffe9",
            "5~CCCAGG~CHIP~DOGE~4~2.9~1514998584~3.48275862~10.099999998~178801142~0~0~0~0~2.9~2.9~2.9~2.9~2.9~2.9~Yobit~7ffe9",
            "5~CCCAGG~CHIP~USD~4~0.0141~1515875673~100~1.41~200000003~0~0~200~2.82~0.0141~0.0141~0.0141~0.00714~0.0141~0.00714~Yobit~7ffe9",
            "5~CCCAGG~CHIP~RUR~4~0.41~1515944977~81.25183855~33.31325299298162~200000019~779.39500606~316.5586349455706~875.593018~350.1210447535757~0.3489~0.41~0.3222~0.07~0.41~0.07~Yobit~7ffe9",
            "5~CCCAGG~CHIP~ETH~4~0.0000898~1515465643~4.92204899~0.00044199999930200003~182641963~0~0~0~0~0.0000898~0.0000898~0.0000898~0.0000898~0.0000898~0.0000898~Yobit~7ffe9",
            "5~CCCAGG~CHIP~WAVES~4~0.00025~1514939041~0.45~0.00011250000000000001~178468201~0~0~0~0~0.00025~0.00025~0.00025~0.00025~0.00025~0.00025~Yobit~7ffe9"
        ]
    },
    "Type": 100
}