{
    "Response": "Success",
    "Message": "This api will soon move to mi-api path.",
    "Data": {
        "Algorithm": "Scrypt",
        "ProofType": "PoW",
        "BlockNumber": 879262,
        "NetHashesPerSecond": 5869178465,
        "TotalCoinsMined": 4993353.9959166,
        "BlockReward": 0.25,
        "AggregatedData": {
            "TYPE": "5",
            "MARKET": "CCCAGG",
            "FROMSYMBOL": "BTA",
            "TOSYMBOL": "BTC",
            "FLAGS": "1",
            "PRICE": "0.00007012",
            "LASTUPDATE": "1516089228",
            "LASTVOLUME": "2.03003",
            "LASTVOLUMETO": "0.00013085573380000002",
            "LASTTRADEID": "1516089228000",
            "VOLUMEDAY": "5012.42118118",
            "VOLUMEDAYTO": "0.3549041346275839",
            "VOLUME24HOUR": "36668.15626024",
            "VOLUME24HOURTO": "2.630523226411799",
            "OPENDAY": "0.00008042",
            "HIGHDAY": "0.00009853",
            "LOWDAY": "0.00006405",
            "OPEN24HOUR": "0.0000822",
            "HIGH24HOUR": "0.0001058",
            "LOW24HOUR": "0.00004094",
            "LASTMARKET": "Bleutrade"
        },
        "Exchanges": [
            {
                "TYPE": "2",
                "MARKET": "BitTrex",
                "FROMSYMBOL": "BTA",
                "TOSYMBOL": "BTC",
                "FLAGS": "2",
                "PRICE": "0.00002933",
                "LASTUPDATE": "1507990170",
                "LASTVOLUME": "93.89718271",
                "LASTVOLUMETO": "0.002754",
                "LASTTRADEID": "5267381",
                "VOLUME24HOUR": "0",
                "VOLUME24HOURTO": "0",
                "OPEN24HOUR": "0.00002933",
                "HIGH24HOUR": "0.00002933",
                "LOW24HOUR": "0.00002933"
            },
            {
                "TYPE": "2",
                "MARKET": "Novaexchange",
                "FROMSYMBOL": "BTA",
                "TOSYMBOL": "BTC",
                "FLAGS": "4",
                "PRICE": "0.00002199",
                "LASTUPDATE": "1510510363",
                "LASTVOLUME": "2.720414",
                "LASTVOLUMETO": "0.000059821903860000004",
                "LASTTRADEID": "1510510363002",
                "VOLUME24HOUR": "9.82819026",
                "VOLUME24HOURTO": "0.0002140159699326",
                "OPEN24HOUR": "0.00002151",
                "HIGH24HOUR": "0.00002199",
                "LOW24HOUR": "0.00002151"
            },
            {
                "TYPE": "2",
                "MARKET": "Cryptopia",
                "FROMSYMBOL": "BTA",
                "TOSYMBOL": "BTC",
                "FLAGS": "1",
                "PRICE": "0.00006616",
                "LASTUPDATE": "1516087975",
                "LASTVOLUME": "10.36538901",
                "LASTVOLUMETO": "0.00068577",
                "LASTTRADEID": "1516087975",
                "VOLUME24HOUR": "28109.659971020003",
                "VOLUME24HOURTO": "1.6119208800000002",
                "OPEN24HOUR": "0.00007897",
                "HIGH24HOUR": "0.00007897",
                "LOW24HOUR": "0.00003131"
            },
            {
                "TYPE": "2",
                "MARKET": "Yobit",
                "FROMSYMBOL": "BTA",
                "TOSYMBOL": "BTC",
                "FLAGS": "2",
                "PRICE": "0.00009008",
                "LASTUPDATE": "1516075040",
                "LASTVOLUME": "13.6621104",
                "LASTVOLUMETO": "0.001230682904832",
                "LASTTRADEID": "200000271",
                "VOLUME24HOUR": "6229.6339766",
                "VOLUME24HOURTO": "0.8549107588361662",
                "OPEN24HOUR": "0.00009796",
                "HIGH24HOUR": "0.00023711",
                "LOW24HOUR": "0.00007862"
            },
            {
                "TYPE": "2",
                "MARKET": "Bleutrade",
                "FROMSYMBOL": "BTA",
                "TOSYMBOL": "BTC",
                "FLAGS": "2",
                "PRICE": "0.00006446",
                "LASTUPDATE": "1516089228",
                "LASTVOLUME": "2.03003",
                "LASTVOLUMETO": "0.00013085573380000002",
                "LASTTRADEID": "1516089228000",
                "VOLUME24HOUR": "2328.862312619999",
                "VOLUME24HOURTO": "0.16369158757563262",
                "OPEN24HOUR": "0.00007896",
                "HIGH24HOUR": "0.00007896",
                "LOW24HOUR": "0.00005638"
            },
            {
                "TYPE": "2",
                "MARKET": "LiveCoin",
                "FROMSYMBOL": "BTA",
                "TOSYMBOL": "BTC",
                "FLAGS": "4",
                "PRICE": "0.00007236",
                "LASTUPDATE": "1515931895",
                "LASTVOLUME": "12.15",
                "LASTVOLUMETO": "0.000879174",
                "LASTTRADEID": "244585026",
                "VOLUME24HOUR": "0",
                "VOLUME24HOURTO": "0",
                "OPEN24HOUR": "0.00007236",
                "HIGH24HOUR": "0.00007236",
                "LOW24HOUR": "0.00007236"
            }
        ]
    },
    "Type": 100
}