{
    "0": {
        "q": "711071527200000",
        "%": "0.0646"
    },
    "1": {
        "q": "711071527200000",
        "%": "0.0646"
    },
    "change": 0,
    "00": {
        "q": "711071527200000",
        "%": "0.0646"
    },
    "01": {
        "q": "711071527200000",
        "%": "0.0646"
    },
    "02": {
        "q": "711071527200000",
        "%": "0.0646"
    },
    "03": {
        "q": "711071527200000",
        "%": "0.0646"
    },
    "05": {
        "q": "711071527200000",
        "%": "0.0646"
    },
    "06": {
        "q": "711071527200000",
        "%": "0.0646"
    },
    "07": {
        "q": "711071527200000",
        "%": "0.0646"
    },
    "08": {
        "q": "711071527200000",
        "%": "0.0646"
    },
    "09": {
        "q": "711071527200000",
        "%": "0.0646"
    },
    "2": {
        "q": "711071527200000",
        "%": "0.0646"
    },
    "3": {
        "q": "711071527200000",
        "%": "0.0646"
    },
    "4": {
        "q": "711071527200000",
        "%": "0.0646"
    },
    "diff": {
        "q": 0,
        "%": 0
    },
    "5": {
        "q": "711071527200000",
        "%": "0.0646"
    },
    "6": {
        "q": "711071527200000",
        "%": "0.0646"
    },
    "7": {
        "q": "711071527200000",
        "%": "0.0646"
    },
    "8": {
        "q": "711071527200000",
        "%": "0.0646"
    },
    "9": {
        "q": "711071527200000",
        "%": "0.0646"
    },
    "10": {
        "q": "711071527200000",
        "%": "0.0646"
    },
    "11": {
        "q": "711071527200000",
        "%": "0.0646"
    }
}