{
    "Response": "Success",
    "Message": "Coin full snapshot successfully returned",
    "Data": {
        "SEO": {
            "PageTitle": "RLC (RLC) - Live streaming prices and market cap",
            "PageDescription": "Live RLC prices from all markets and RLC coin market Capitalization. Stay up to date with the latest RLC price movements and forum discussion. Check out our snapshot charts and see when there is an opportunity to buy or sell.",
            "BaseUrl": "https:\/\/www.cryptocompare.com",
            "BaseImageUrl": "https:\/\/www.cryptocompare.com",
            "OgImageUrl": "\/media\/12318418\/rlc.png",
            "OgImageWidth": "300",
            "OgImageHeight": "300"
        },
        "General": {
            "Id": "61877",
            "DocumentType": "Webpagecoinp",
            "H1Text": "RLC (RLC)",
            "DangerTop": "",
            "WarningTop": "",
            "InfoTop": "",
            "Symbol": "RLC",
            "Url": "\/coins\/rlc\/",
            "BaseAngularUrl": "\/coins\/rlc\/",
            "Name": "iEx.ec",
            "ImageUrl": "\/media\/12318418\/rlc.png",
            "Description": "<p><span>RLC is an Ethereum-based token\u00a0used in the\u00a0iEx.ec, a blockchain-based distributed cloud computing platform.\u00a0\u00a0Developers can rent computing power, servers and data centers and make their unused resources available through a unique marketplace on the Ethereum blockchain. The RLC token allows users to\u00a0rent servers, data and applications to execute their distributed applications.<\/span><\/p>",
            "Features": "",
            "Technology": "",
            "TotalCoinSupply": " 87000000",
            "Algorithm": "",
            "ProofType": "",
            "StartDate": "10\/01\/2017",
            "Twitter": "@iEx_ec",
            "AffiliateUrl": "http:\/\/iex.ec\/",
            "Website": "<a href='http:\/\/iex.ec\/' target='_blank'>iEx.ec<\/a>",
            "Sponsor": {
                "TextTop": "Sponsored by",
                "Link": "http:\/\/wepowernetwork.go2cloud.org\/aff_c?offer_id=2&aff_id=1001",
                "ImageUrl": "\/media\/20780605\/2.png"
            },
            "LastBlockExplorerUpdateTS": 1515969922,
            "DifficultyAdjustment": null,
            "BlockRewardReduction": null,
            "BlockNumber": 0,
            "BlockTime": 0,
            "NetHashesPerSecond": 0,
            "TotalCoinsMined": 86999784.986845,
            "PreviousTotalCoinsMined": 0,
            "BlockReward": 0
        },
        "ICO": {
            "Status": "Finished",
            "Description": "<p><span data-sheets-value=\"{&quot;1&quot;:2,&quot;2&quot;:&quot;2 hours 45 mins&quot;}\" data-sheets-userformat=\"{&quot;2&quot;:12456,&quot;6&quot;:{&quot;1&quot;:[{&quot;1&quot;:2,&quot;2&quot;:0,&quot;5&quot;:[null,2,0]},{&quot;1&quot;:0,&quot;2&quot;:0,&quot;3&quot;:3},{&quot;1&quot;:1,&quot;2&quot;:0,&quot;4&quot;:1}]},&quot;8&quot;:{&quot;1&quot;:[{&quot;1&quot;:2,&quot;2&quot;:0,&quot;5&quot;:[null,2,0]},{&quot;1&quot;:0,&quot;2&quot;:0,&quot;3&quot;:3},{&quot;1&quot;:1,&quot;2&quot;:0,&quot;4&quot;:1}]},&quot;10&quot;:2,&quot;15&quot;:&quot;Calibri&quot;,&quot;16&quot;:11}\"><span>\u00a0<\/span><span>RLC is an Ethereum\u00a0ERC20 token\u00a0used in the\u00a0iEx.ec, a blockchain-based distributed cloud computing platform. \u00a0The RLC token allows users to\u00a0rent servers, data and applications to execute their distributed applications.<\/span><\/span><\/p><p><span data-sheets-value=\"{&quot;1&quot;:2,&quot;2&quot;:&quot;2 hours 45 mins&quot;}\" data-sheets-userformat=\"{&quot;2&quot;:12456,&quot;6&quot;:{&quot;1&quot;:[{&quot;1&quot;:2,&quot;2&quot;:0,&quot;5&quot;:[null,2,0]},{&quot;1&quot;:0,&quot;2&quot;:0,&quot;3&quot;:3},{&quot;1&quot;:1,&quot;2&quot;:0,&quot;4&quot;:1}]},&quot;8&quot;:{&quot;1&quot;:[{&quot;1&quot;:2,&quot;2&quot;:0,&quot;5&quot;:[null,2,0]},{&quot;1&quot;:0,&quot;2&quot;:0,&quot;3&quot;:3},{&quot;1&quot;:1,&quot;2&quot;:0,&quot;4&quot;:1}]},&quot;10&quot;:2,&quot;15&quot;:&quot;Calibri&quot;,&quot;16&quot;:11}\">The RLC ICO sold the available\u00a060,000,000\u00a0tokens available in under 3 hours and the capital of over $12,000,000 was raised by 1200 buyers. RLC could be bought at a discount of 20% for the first 10 days at a rate of\u00a0<\/span><\/p><p>1 BTC = 5000 RLC<\/p><p>1ETH = 205 RLC<\/p><p><span data-sheets-value=\"{&quot;1&quot;:2,&quot;2&quot;:&quot;2 hours 45 mins&quot;}\" data-sheets-userformat=\"{&quot;2&quot;:12456,&quot;6&quot;:{&quot;1&quot;:[{&quot;1&quot;:2,&quot;2&quot;:0,&quot;5&quot;:[null,2,0]},{&quot;1&quot;:0,&quot;2&quot;:0,&quot;3&quot;:3},{&quot;1&quot;:1,&quot;2&quot;:0,&quot;4&quot;:1}]},&quot;8&quot;:{&quot;1&quot;:[{&quot;1&quot;:2,&quot;2&quot;:0,&quot;5&quot;:[null,2,0]},{&quot;1&quot;:0,&quot;2&quot;:0,&quot;3&quot;:3},{&quot;1&quot;:1,&quot;2&quot;:0,&quot;4&quot;:1}]},&quot;10&quot;:2,&quot;15&quot;:&quot;Calibri&quot;,&quot;16&quot;:11}\"><span data-sheets-value=\"{&quot;1&quot;:3,&quot;3&quot;:1200}\" data-sheets-userformat=\"{&quot;2&quot;:12520,&quot;6&quot;:{&quot;1&quot;:[{&quot;1&quot;:2,&quot;2&quot;:0,&quot;5&quot;:{&quot;1&quot;:2,&quot;2&quot;:0}},{&quot;1&quot;:0,&quot;2&quot;:0,&quot;3&quot;:3},{&quot;1&quot;:1,&quot;2&quot;:0,&quot;4&quot;:1}]},&quot;8&quot;:{&quot;1&quot;:[{&quot;1&quot;:2,&quot;2&quot;:0,&quot;5&quot;:{&quot;1&quot;:2,&quot;2&quot;:0}},{&quot;1&quot;:0,&quot;2&quot;:0,&quot;3&quot;:3},{&quot;1&quot;:1,&quot;2&quot;:0,&quot;4&quot;:1}]},&quot;9&quot;:2,&quot;10&quot;:2,&quot;15&quot;:&quot;Calibri&quot;,&quot;16&quot;:11}\"><a href=\"http:\/\/iex.ec\/roadmap\" target=\"_blank\" title=\"Roadmap\">Roadmap\u00a0<\/a><span data-sheets-value=\"{&quot;1&quot;:2,&quot;2&quot;:&quot;http:\/\/iex.ec\/roadmap&quot;}\" data-sheets-userformat=\"{&quot;2&quot;:268416,&quot;10&quot;:2,&quot;14&quot;:[null,2,1136076],&quot;15&quot;:&quot;arial,sans,sans-serif&quot;,&quot;21&quot;:1}\"><a href=\"http:\/\/iex.ec\/roadmap\" target=\"_blank\" class=\"in-cell-link\"><\/a><\/span><\/span><\/span><\/p><p>\u00a0<\/p>",
            "TokenType": "ETH (ERC20)",
            "Website": "<a href='http:\/\/crowdsale.iex.ec\/' target='_blank'>Go To Sale Website<\/a>",
            "WebsiteLink": "http:\/\/crowdsale.iex.ec\/",
            "PublicPortfolioUrl": "-",
            "PublicPortfolioId": "N\/A",
            "Features": "Bonus,Cap,Bounties",
            "FundingTarget": "N\/A",
            "FundingCap": "12,000,000 USD",
            "ICOTokenSupply": "86999784",
            "TokenSupplyPostICO": "Remains Unchanged",
            "TokenPercentageForInvestors": "68.96",
            "TokenReserveSplit": "17.55% T, 6.89% B, 6.6% O",
            "Date": 1492606800,
            "EndDate": 1492616700,
            "FundsRaisedList": "2,761.761 BTC; 173,886 ETH",
            "FundsRaisedUSD": "12158963",
            "StartPrice": "0.25",
            "StartPriceCurrency": "USD",
            "PaymentMethod": "ETH,BTC",
            "Jurisdiction": "N\/A",
            "LegalAdvisers": "N\/A",
            "LegalForm": "N\/A",
            "SecurityAuditCompany": "N\/A",
            "Blog": "<a href='https:\/\/medium.com\/iex-ec' target='_blank'>Vist Blog<\/a>",
            "BlogLink": "https:\/\/medium.com\/iex-ec",
            "WhitePaper": "<a href='http:\/\/iex.ec\/?page_id=186' target='_blank'>Read Whitepaper<\/a>",
            "WhitePaperLink": "http:\/\/iex.ec\/?page_id=186"
        },
        "Subs": [
            "2~LiveCoin~RLC~BTC",
            "2~Novaexchange~RLC~DOGE",
            "2~LiveCoin~RLC~USD",
            "2~Novaexchange~RLC~LTC",
            "2~Novaexchange~RLC~ESP2",
            "2~HitBTC~RLC~BTC",
            "2~Novaexchange~RLC~BTC",
            "2~BitTrex~RLC~ETH",
            "2~Gateio~RLC~ETH",
            "2~LiveCoin~RLC~ETH",
            "2~EtherDelta~RLC~ETH",
            "2~Novaexchange~RLC~ETH",
            "2~Liqui~RLC~ETH",
            "2~Liqui~RLC~USDT",
            "2~Liqui~RLC~BTC",
            "2~BitTrex~RLC~BTC",
            "2~Tidex~RLC~BTC",
            "2~Gatecoin~RLC~BTC"
        ],
        "StreamerDataRaw": [
            "5~CCCAGG~RLC~BTC~4~0.0002564~1515978462~15~0.0037867499999999998~152405317~82347.47962557005~21.105116440920987~1603461.7569217004~415.28815826622133~0.000269~0.000269~0.0002513~0.0002356~0.0002937~0.0002252~HitBTC~7ffe9",
            "5~CCCAGG~RLC~DOGE~4~16.00000038~1509703425~0.93451807~14.952289475116865~1509703425001~0~0~0~0~16~16.00000038~16~16.00000038~16.00000038~16.00000038~Novaexchange~7ffe9",
            "5~CCCAGG~RLC~USD~4~4.00016~1515762277~3.674853~14.699999976480001~242244995~0~0~0~0~4~4.00016~4~4.00016~4.00016~4.00016~LiveCoin~7ffe9",
            "5~CCCAGG~RLC~LTC~4~0.5~1501131182~0.0002~0.0001~1501131182000~0~0~0~0~0.5~0.5~0.5~0.5~0.5~0.5~Novaexchange~7ffe9",
            "5~CCCAGG~RLC~ESP2~4~12~1501139203~0.08384766~1.00617192~1501139203000~0~0~0~0~12~12~12~12~12~12~Novaexchange~7ffe9",
            "5~CCCAGG~RLC~ETH~4~0.002557~1515978251~2.55180099~0.0065757359711309995~62275711~3343.7178003600015~8.559718797060619~81973.992888497~216.33536946624707~0.002688~0.002688~0.002534~0.002475~0.003014~0.002392~Liqui~7ffe9",
            "5~CCCAGG~RLC~USDT~4~3.42~1515978012~1.76630616~6.047622331026761~62274654~839.7039665200004~2885.0418881179426~10339.775933690002~35246.0745471927~3.5~3.5~3.37~3.37~3.57~3.18~Liqui~7ffe9"
        ]
    },
    "Type": 100
}